base62/__init__.py
base62/__main__.py
base62/base62.py
base62/decoder.py
base62/encoder.py
base62_py-1.3.15.dist-info/licenses/LICENSE
base62_py-1.3.15.dist-info/METADATA
base62_py-1.3.15.dist-info/WHEEL
base62_py-1.3.15.dist-info/entry_points.txt
base62_py-1.3.15.dist-info/top_level.txt
base62_py-1.3.15.dist-info/RECORD
