Metadata-Version: 2.4
Name: base62-py
Version: 1.3.15
Summary: Custom Base-62 Encoder in Python
Author-email: Cyril Dever <cdever@pep-s.com>
License: MIT License
Project-URL: Homepage, https://github.com/cyrildever/base62
Keywords: base62,base-62,encoder,decoder
Classifier: Programming Language :: Python :: 3
Classifier: License :: OSI Approved :: MIT License
Classifier: Operating System :: OS Independent
Requires-Python: >=3.10.2
License-File: LICENSE
Requires-Dist: py-utls>=0.3.1
Dynamic: license-file
